lostc/__init__.py
lostc/collection.py
lostc/combine.py
lostc/ip.py
lostc/range.py
lostc-0.1.0.dist-info/LICENSE
lostc-0.1.0.dist-info/METADATA
lostc-0.1.0.dist-info/WHEEL
lostc-0.1.0.dist-info/top_level.txt
lostc-0.1.0.dist-info/RECORD
