Metadata-Version: 2.1
Name: lostc
Version: 0.1.0
Summary: # Just some ez codes
